nipals/__init__.py
nipals/nipals.py
nipals-0.5.8.dist-info/AUTHORS.rst
nipals-0.5.8.dist-info/LICENSE
nipals-0.5.8.dist-info/METADATA
nipals-0.5.8.dist-info/WHEEL
nipals-0.5.8.dist-info/top_level.txt
nipals-0.5.8.dist-info/RECORD
