Metadata-Version: 2.1
Name: nipals
Version: 0.5.8
Summary: A module for calculation of PCA with the NIPALS algorithm
Home-page: https://github.com/fredrikw/python-nipals
Author: Fredrik Wallner
Author-email: fredrik@wallner.nu
License: MIT license
Classifier: Development Status :: 4 - Beta
Classifier: Intended Audience :: Developers
Classifier: Intended Audience :: Science/Research
Classifier: License :: OSI Approved :: MIT License
Classifier: Operating System :: Unix
Classifier: Operating System :: POSIX
Classifier: Operating System :: Microsoft :: Windows
Classifier: Programming Language :: Python
Classifier: Programming Language :: Python :: 3
Classifier: Programming Language :: Python :: 3.8
Classifier: Programming Language :: Python :: 3.9
Classifier: Programming Language :: Python :: 3.10
Classifier: Programming Language :: Python :: 3.11
Classifier: Programming Language :: Python :: 3.12
Classifier: Programming Language :: Python :: Implementation :: CPython
Classifier: Topic :: Utilities
Classifier: Topic :: Scientific/Engineering
Classifier: Topic :: Scientific/Engineering :: Bio-Informatics
Classifier: Topic :: Scientific/Engineering :: Chemistry
License-File: LICENSE
License-File: AUTHORS.rst
Requires-Dist: pandas>=0.22
Requires-Dist: scipy>=1.0.0
Requires-Dist: matplotlib>2.0.0
